textcmp/pyproject.toml
textcmp/README.rst
textcmp/tests/__init__.py
textcmp/tests/test_textcmp.py
textcmp/textcmp/__init__.py
textcmp-0.1.1.dist-info/WHEEL
textcmp-0.1.1.dist-info/METADATA
textcmp-0.1.1.dist-info/RECORD
